gshttpservice/VERSION
gshttpservice/__init__.py
gshttpservice/__main__.py
gshttpservice/server.py
gshttpservice/utils.py
gshttpservice/version.py
gshttpservice/tests/__init__.py
gshttpservice/tests/test_service.py
gshttpservice-0.1.0.dist-info/METADATA
gshttpservice-0.1.0.dist-info/WHEEL
gshttpservice-0.1.0.dist-info/top_level.txt
gshttpservice-0.1.0.dist-info/RECORD
