Metadata-Version: 2.1
Name: gshttpservice
Version: 0.1.0
Summary: Http server wrapper for standalone GraphScope
Home-page: https://github.com/GraphScope/gshttpservice
Author: GraphScope team of Damo Academy
Author-email: graphscope@alibaba-inc.com
License: Apache License 2.0
Keywords: GraphScope,Graph Computations
Classifier: Development Status :: 5 - Production/Stable
Classifier: Intended Audience :: Developers
Classifier: License :: OSI Approved :: Apache Software License
Classifier: Topic :: Software Development :: Libraries
Classifier: Topic :: System :: Distributed Computing
Classifier: Operating System :: MacOS :: MacOS X
Classifier: Operating System :: POSIX
Classifier: Programming Language :: Python
Classifier: Programming Language :: Python :: 3
Classifier: Programming Language :: Python :: 3.7
Classifier: Programming Language :: Python :: 3.8
Classifier: Programming Language :: Python :: 3.9
Requires-Dist: graphscope (>=0.15.0)
Provides-Extra: dev
Requires-Dist: black (==22.3.0) ; extra == 'dev'
Requires-Dist: flake8 (==4.0.1) ; extra == 'dev'
Requires-Dist: isort (==5.10.1) ; extra == 'dev'
